irt2/__init__.py
irt2/cli.py
irt2/dataset.py
irt2/evaluation.py
irt2/graph.py
irt2/loader/__init__.py
irt2/loader/blp_loader.py
irt2/loader/irt2_loader.py
irt2/types.py
irt2-1.1.0.dist-info/LICENSE
irt2-1.1.0.dist-info/METADATA
irt2-1.1.0.dist-info/WHEEL
irt2-1.1.0.dist-info/entry_points.txt
irt2-1.1.0.dist-info/RECORD
