Metadata-Version: 2.1
Name: irt2
Version: 1.1.0
Summary: IRT2 - Inductive Reasoning with Text
License: MIT
Author: Felix Hamann
Author-email: felix@hamann.xyz
Requires-Python: >=3.11,<4.0
Classifier: License :: OSI Approved :: MIT License
Classifier: Programming Language :: Python :: 3
Classifier: Programming Language :: Python :: 3.11
Classifier: Programming Language :: Python :: 3.12
Requires-Dist: click (>=8.1.7,<9.0.0)
Requires-Dist: jupyter (>=1.0.0,<2.0.0)
Requires-Dist: ktz (>=0.4.0,<0.5.0)
Requires-Dist: matplotlib (>=3.8.4,<4.0.0)
Requires-Dist: networkx (>=3.3,<4.0)
Requires-Dist: pretty-errors (>=1.2.25,<2.0.0)
Requires-Dist: pyyaml (>=6.0.1,<7.0.0)
Requires-Dist: rich-click (>=1.7.4,<2.0.0)
Requires-Dist: tabulate (>=0.9.0,<0.10.0)
